wsit/__init__.py
wsit/rpc_client.py
wsit/main/__init__.py
wsit/main/com/__init__.py
wsit/main/com/vsi/__init__.py
wsit/main/com/vsi/wsi/__init__.py
wsit/main/com/vsi/wsi/big_decimal.py
wsit/main/com/vsi/wsi/i_wsi_native_shell.py
wsit/main/com/vsi/wsi/i_xa_resource.py
wsit/main/com/vsi/wsi/i_xid.py
wsit/main/com/vsi/wsi/invalid_state_exception.py
wsit/main/com/vsi/wsi/no_server_exception.py
wsit/main/com/vsi/wsi/server_config.py
wsit/main/com/vsi/wsi/string_qualify.py
wsit/main/com/vsi/wsi/wsi_acms_context.py
wsit/main/com/vsi/wsi/wsi_acms_context_editor.py
wsit/main/com/vsi/wsi/wsi_array.py
wsit/main/com/vsi/wsi/wsi_buffer.py
wsit/main/com/vsi/wsi/wsi_connect_exception.py
wsit/main/com/vsi/wsi/wsi_decimal.py
wsit/main/com/vsi/wsi/wsi_exception.py
wsit/main/com/vsi/wsi/wsi_ipc_context.py
wsit/main/com/vsi/wsi/wsi_msg_packager.py
wsit/main/com/vsi/wsi/wsi_rtl_version.py
wsit/main/com/vsi/wsi/wsi_server_exception.py
wsit/main/com/vsi/wsi/wsi_structure.py
wsit/main/com/vsi/wsi/wsi_utils.py
wsit/main/com/vsi/wsi/wsi_v2_structure.py
wsit/main/com/vsi/wsi/wsi_xa_desc.py
wsit/main/com/vsi/wsi/wsi_xid_cache.py
wsit/main/com/vsi/wsi/wsi_xid_impl.py
wsit/main/com/vsi/wsi/wsi_xid_map.py
wsit/main/com/vsi/wsi/xa_exception.py
wsit/main/pyx/__init__.py
wsit/main/pyx/xml/__init__.py
wsit/main/pyx/xml/rpc/__init__.py
wsit/main/pyx/xml/rpc/holders/__init__.py
wsit/main/pyx/xml/rpc/holders/array_holder.py
wsit/main/pyx/xml/rpc/holders/array_holder_editor.py
wsit/main/pyx/xml/rpc/holders/big_decimal_editor.py
wsit/main/pyx/xml/rpc/holders/big_decimal_holder.py
wsit/main/pyx/xml/rpc/holders/big_decimal_holder_editor.py
wsit/main/pyx/xml/rpc/holders/big_integer_editor.py
wsit/main/pyx/xml/rpc/holders/big_integer_holder.py
wsit/main/pyx/xml/rpc/holders/big_integer_holder_editor.py
wsit/main/pyx/xml/rpc/holders/boolean_holder.py
wsit/main/pyx/xml/rpc/holders/boolean_holder_editor.py
wsit/main/pyx/xml/rpc/holders/byte_holder.py
wsit/main/pyx/xml/rpc/holders/byte_holder_editor.py
wsit-1.0.17.dist-info/LICENSE.md
wsit-1.0.17.dist-info/METADATA
wsit-1.0.17.dist-info/WHEEL
wsit-1.0.17.dist-info/top_level.txt
wsit-1.0.17.dist-info/RECORD
