Metadata-Version: 2.1
Name: wsit
Version: 1.0.17
Summary: Web Services Integration Toolkit
Home-page: https://vmssoftware.com/products/web-services-integration-toolkit/
Author: VMS Software, Inc.
License: MIT
Platform: UNKNOWN
Requires-Dist: python-interface
Requires-Dist: numpy
Requires-Dist: pytest
Requires-Dist: pika
